{"cameraMode":{"drawMode":0,"name":"Shaded","section":"Shading Mode"},"sceneLighting":false,"audioPlay":false,"sceneViewState":{"m_AlwaysRefresh":false,"showFog":true,"showSkybox":false,"showFlares":true,"showImageEffects":true,"showParticleSystems":true,"showVisualEffectGraphs":true,"m_FxEnabled":true},"in2DMode":false,"pivot":{"x":0.026165485382080079,"y":9.433571815490723,"z":-0.11867523193359375},"rotation":{"x":0.08538421988487244,"y":-0.016437672078609468,"z":0.0014103346038609744,"w":0.9962143301963806},"size":6.610772609710693,"orthographic":false}